{
    "variants": {
        "variant=stone": [
            { "model": "iberia:hardstone" },
            { "model": "iberia:hardstone" },
            { "model": "iberia:hardstone", "y": 180 },
            { "model": "iberia:hardstone", "y": 180 }
        ],
        "variant=andesite": { "model": "iberia:hardandesite" },
        "variant=diorite": { "model": "iberia:harddiorite" },
        "variant=granite": { "model": "iberia:hardgranite" },
        "variant=smooth_andesite": { "model": "iberia:hardandesite_smooth" },
        "variant=smooth_diorite": { "model": "iberia:harddiorite_smooth" },
        "variant=smooth_granite": { "model": "iberia:hardgranite_smooth" },
        "inventory": { "model": "stone" }
    }
}